{
  "project_info": {
    "project_number": "1084347658038",
    "firebase_url": "https://intouchsmsapp-af420.firebaseio.com",
    "project_id": "intouchsmsapp-af420",
    "storage_bucket": "intouchsmsapp-af420.appspot.com"
  },
  "client": [
    {
      "client_info": {
        "mobilesdk_app_id": "1:1084347658038:android:af2b9eb65535de6a148d97",
        "android_client_info": {
          "package_name": "com.example.root.intouchsmsapp"
        }
      },
      "oauth_client": [
        {
          "client_id": "1084347658038-vgsv6ckrjkf36l4t0b2viomp58kj1gkv.apps.googleusercontent.com",
          "client_type": 1,
          "android_info": {
            "package_name": "com.example.root.intouchsmsapp",
            "certificate_hash": "8782786d9b4b2e580a625569afeb1cded307df12"
          }
        },
        {
          "client_id": "1084347658038-l16ttncjlnd8ecou7v91qm31jrv8rld2.apps.googleusercontent.com",
          "client_type": 3
        }
      ],
      "api_key": [
        {
          "current_key": "AIzaSyBEw8MVf6WdazrpgRDGryG9S6OUregTML0"
        }
      ],
      "services": {
        "appinvite_service": {
          "other_platform_oauth_client": [
            {
              "client_id": "1084347658038-l16ttncjlnd8ecou7v91qm31jrv8rld2.apps.googleusercontent.com",
              "client_type": 3
            }
          ]
        }
      }
    }
  ],
  "configuration_version": "1"
}